desilofhe.cpython-311-x86_64-linux-gnu.so
desilofhe_cu128-1.8.0.dist-info/METADATA
desilofhe_cu128-1.8.0.dist-info/WHEEL
desilofhe_cu128-1.8.0.dist-info/RECORD
desilofhe_cu128-1.8.0.dist-info/licenses/LICENSE
