Metadata-Version: 2.4
Name: desilofhe-cu128
Version: 1.8.0
Summary: The DESILO Fully Homomorphic Encryption (FHE) library
Keywords: DESILO,python,cryptography,privacy,encryption,cuda,homomorphic encryption,homomorphic encryption library,fully homomorphic encryption,fhe,gpu accelerated
Author-Email: Desilo Library Team <library@desilo.ai>, Eunmo Yang <eunmo.yang@desilo.ai>
Maintainer-Email: Desilo Library Team <library@desilo.ai>, Eunmo Yang <eunmo.yang@desilo.ai>
License-File: LICENSE
Classifier: Environment :: GPU :: NVIDIA CUDA
Classifier: Programming Language :: Python
Classifier: Topic :: Software Development :: Libraries
Project-URL: Homepage, https://desilo.ai/
Project-URL: Documentation, https://fhe.desilo.dev/
Requires-Python: >=3.10
Requires-Dist: numpy>=1.26.0
